{
    "id": "Aadhar_63",
    "full_text": [
        "GOVERNMENT",
        "OF",
        "IONI",
        "/Name:",
        "shivanandbelluli",
        "Male",
        "1472",
        "58369074"
    ],
    "bbox": [
        [
            [
                285,
                65
            ],
            [
                511,
                61
            ],
            [
                511,
                89
            ],
            [
                286,
                93
            ]
        ],
        [
            [
                518,
                67
            ],
            [
                558,
                67
            ],
            [
                558,
                85
            ],
            [
                518,
                85
            ]
        ],
        [
            [
                572,
                65
            ],
            [
                640,
                65
            ],
            [
                640,
                85
            ],
            [
                572,
                85
            ]
        ],
        [
            [
                260,
                181
            ],
            [
                460,
                179
            ],
            [
                461,
                219
            ],
            [
                260,
                220
            ]
        ],
        [
            [
                262,
                227
            ],
            [
                548,
                227
            ],
            [
                548,
                264
            ],
            [
                262,
                264
            ]
        ],
        [
            [
                262,
                330
            ],
            [
                353,
                330
            ],
            [
                353,
                371
            ],
            [
                262,
                371
            ]
        ],
        [
            [
                269,
                461
            ],
            [
                429,
                461
            ],
            [
                429,
                514
            ],
            [
                269,
                514
            ]
        ],
        [
            [
                401,
                459
            ],
            [
                672,
                459
            ],
            [
                672,
                514
            ],
            [
                401,
                514
            ]
        ]
    ],
    "confidence": [
        0.994185745716095,
        0.9823106527328491,
        0.8874558806419373,
        0.9615817666053772,
        0.98573899269104,
        0.9983986616134644,
        0.9992982149124146,
        0.999596893787384
    ],
    "label": "Aadhar",
    "image_path": "./data/raw_images/Aadhar/Aadhar_63.jpg"
}