{
    "id": "Aadhar_14",
    "full_text": [
        "Unique ldentificationAuthority of India",
        "AADHAAR",
        "R-121001",
        "Address:",
        "W/O:Narender Gera, 2F-63,WARD11-NH,2,",
        "FaridabadFaridabad",
        "Haryana-121001",
        "322339994990",
        "VID:9152509410656905",
        "1947",
        "help",
        "@uidai.gov.in",
        "ai.gov.in"
    ],
    "bbox": [
        [
            [
                233,
                57
            ],
            [
                853,
                65
            ],
            [
                852,
                101
            ],
            [
                232,
                93
            ]
        ],
        [
            [
                927,
                85
            ],
            [
                1039,
                85
            ],
            [
                1039,
                103
            ],
            [
                927,
                103
            ]
        ],
        [
            [
                25,
                187
            ],
            [
                231,
                191
            ],
            [
                230,
                221
            ],
            [
                24,
                216
            ]
        ],
        [
            [
                21,
                236
            ],
            [
                153,
                238
            ],
            [
                153,
                268
            ],
            [
                21,
                266
            ]
        ],
        [
            [
                20,
                262
            ],
            [
                610,
                266
            ],
            [
                610,
                297
            ],
            [
                20,
                293
            ]
        ],
        [
            [
                23,
                294
            ],
            [
                303,
                294
            ],
            [
                303,
                320
            ],
            [
                23,
                320
            ]
        ],
        [
            [
                23,
                321
            ],
            [
                252,
                321
            ],
            [
                252,
                347
            ],
            [
                23,
                347
            ]
        ],
        [
            [
                335,
                490
            ],
            [
                684,
                490
            ],
            [
                684,
                531
            ],
            [
                335,
                531
            ]
        ],
        [
            [
                328,
                541
            ],
            [
                718,
                541
            ],
            [
                718,
                572
            ],
            [
                328,
                572
            ]
        ],
        [
            [
                121,
                591
            ],
            [
                187,
                588
            ],
            [
                188,
                606
            ],
            [
                122,
                609
            ]
        ],
        [
            [
                371,
                589
            ],
            [
                433,
                589
            ],
            [
                433,
                604
            ],
            [
                371,
                604
            ]
        ],
        [
            [
                425,
                587
            ],
            [
                618,
                587
            ],
            [
                618,
                605
            ],
            [
                425,
                605
            ]
        ],
        [
            [
                879,
                588
            ],
            [
                994,
                588
            ],
            [
                994,
                602
            ],
            [
                879,
                602
            ]
        ]
    ],
    "confidence": [
        0.931428074836731,
        0.9972332715988159,
        0.9863650798797607,
        0.980508029460907,
        0.920259416103363,
        0.9605376124382019,
        0.985632598400116,
        0.9990894794464111,
        0.9649873971939087,
        0.9980645775794983,
        0.9788793921470642,
        0.9562897086143494,
        0.9700831174850464
    ],
    "label": "Aadhar",
    "image_path": "./data/raw_images/Aadhar/Aadhar_14.jpeg"
}