{
    "id": "pan_57",
    "full_text": [
        "INCOMETAX DEPARTMENT",
        "GOVT OF INDIA",
        "Permanent Account Number Card",
        "ABCDE1234F",
        "T/Name",
        "APPLICANTNAME",
        "APPLICANT'S FATHER NAME",
        "Siguature",
        "Date of Birth",
        "01/06/1995"
    ],
    "bbox": [
        [
            [
                23,
                206
            ],
            [
                231,
                213
            ],
            [
                231,
                235
            ],
            [
                23,
                227
            ]
        ],
        [
            [
                338,
                213
            ],
            [
                501,
                217
            ],
            [
                500,
                239
            ],
            [
                337,
                235
            ]
        ],
        [
            [
                131,
                255
            ],
            [
                343,
                261
            ],
            [
                343,
                278
            ],
            [
                131,
                273
            ]
        ],
        [
            [
                184,
                273
            ],
            [
                321,
                277
            ],
            [
                320,
                297
            ],
            [
                184,
                292
            ]
        ],
        [
            [
                26,
                313
            ],
            [
                90,
                315
            ],
            [
                89,
                329
            ],
            [
                25,
                326
            ]
        ],
        [
            [
                34,
                325
            ],
            [
                187,
                328
            ],
            [
                187,
                345
            ],
            [
                33,
                342
            ]
        ],
        [
            [
                32,
                357
            ],
            [
                273,
                366
            ],
            [
                272,
                385
            ],
            [
                32,
                376
            ]
        ],
        [
            [
                164,
                379
            ],
            [
                327,
                384
            ],
            [
                326,
                413
            ],
            [
                163,
                408
            ]
        ],
        [
            [
                23,
                391
            ],
            [
                88,
                395
            ],
            [
                88,
                408
            ],
            [
                23,
                405
            ]
        ],
        [
            [
                31,
                404
            ],
            [
                119,
                408
            ],
            [
                118,
                425
            ],
            [
                30,
                421
            ]
        ]
    ],
    "confidence": [
        0.9703853726387024,
        0.9163303375244141,
        0.9684225916862488,
        0.9911884069442749,
        0.8372676968574524,
        0.9977709054946899,
        0.9689155220985413,
        0.9198306202888489,
        0.9287285208702087,
        0.9936951398849487
    ],
    "label": "pan",
    "image_path": "./data/raw_images/pan/pan_57.jpg"
}